{
  "text": "και ειπον αυτω κυριε εχει δεκα μνας",
  "words": [
    {
      "position": 1,
      "text": "και",
      "lemma": [
        "G2532"
      ],
      "morph": "robinson:CONJ",
      "strongs": "G2532",
      "metadata": {},
      "gematria": {
        "standard": 31,
        "ordinal": 20,
        "reduced": 4
      }
    },
    {
      "position": 2,
      "text": "ειπον",
      "lemma": [
        "G3004"
      ],
      "morph": "robinson:V-2AAI-3P",
      "strongs": "G3004",
      "metadata": {},
      "gematria": {
        "standard": 215,
        "ordinal": 58,
        "reduced": 8
      }
    },
    {
      "position": 3,
      "text": "αυτω",
      "lemma": [
        "G846"
      ],
      "morph": "robinson:P-DSM",
      "strongs": "G846",
      "metadata": {},
      "gematria": {
        "standard": 1501,
        "ordinal": 64,
        "reduced": 7
      }
    },
    {
      "position": 4,
      "text": "κυριε",
      "lemma": [
        "G2962"
      ],
      "morph": "robinson:N-VSM",
      "strongs": "G2962",
      "metadata": {},
      "gematria": {
        "standard": 535,
        "ordinal": 61,
        "reduced": 4
      }
    },
    {
      "position": 5,
      "text": "εχει",
      "lemma": [
        "G2192"
      ],
      "morph": "robinson:V-PAI-3S",
      "strongs": "G2192",
      "metadata": {},
      "gematria": {
        "standard": 620,
        "ordinal": 41,
        "reduced": 8
      }
    },
    {
      "position": 6,
      "text": "δεκα",
      "lemma": [
        "G1176"
      ],
      "morph": "robinson:A-NUI",
      "strongs": "G1176",
      "metadata": {},
      "gematria": {
        "standard": 30,
        "ordinal": 20,
        "reduced": 3
      }
    },
    {
      "position": 7,
      "text": "μνας",
      "lemma": [
        "G3414"
      ],
      "morph": "robinson:N-APF",
      "strongs": "G3414",
      "metadata": {},
      "gematria": {
        "standard": 291,
        "ordinal": 44,
        "reduced": 3
      }
    }
  ],
  "gematria": {
    "standard": 3223,
    "ordinal": 308,
    "reduced": 37
  }
}