{
  "text": "σφοδρως δε χειμαζομενων ημων τη εxης εκβολην εποιουντο",
  "words": [
    {
      "position": 1,
      "text": "σφοδρως",
      "lemma": [
        "G4971"
      ],
      "morph": "robinson:ADV",
      "strongs": "G4971",
      "metadata": {},
      "gematria": {
        "standard": 1874,
        "ordinal": 28,
        "reduced": 29
      }
    },
    {
      "position": 2,
      "text": "δε",
      "lemma": [
        "G1161"
      ],
      "morph": "robinson:CONJ",
      "strongs": "G1161",
      "metadata": {},
      "gematria": {
        "standard": 9,
        "ordinal": 3,
        "reduced": 9
      }
    },
    {
      "position": 3,
      "text": "χειμαζομενων",
      "lemma": [
        "G5492"
      ],
      "morph": "robinson:V-PPP-GPM",
      "strongs": "G5492",
      "metadata": {},
      "gematria": {
        "standard": 1678,
        "ordinal": 78,
        "reduced": 58
      }
    },
    {
      "position": 4,
      "text": "ημων",
      "lemma": [
        "G1473"
      ],
      "morph": "robinson:P-1GP",
      "strongs": "G1473",
      "metadata": {},
      "gematria": {
        "standard": 898,
        "ordinal": 10,
        "reduced": 25
      }
    },
    {
      "position": 5,
      "text": "τη",
      "lemma": [
        "G3588"
      ],
      "morph": "robinson:T-DSF",
      "strongs": "G3588",
      "metadata": {},
      "gematria": {
        "standard": 308,
        "ordinal": 3,
        "reduced": 11
      }
    },
    {
      "position": 6,
      "text": "εxης",
      "lemma": [
        "G1836"
      ],
      "morph": "robinson:ADV",
      "strongs": "G1836",
      "metadata": {},
      "gematria": {
        "standard": 213,
        "ordinal": 6,
        "reduced": 15
      }
    },
    {
      "position": 7,
      "text": "εκβολην",
      "lemma": [
        "G1546"
      ],
      "morph": "robinson:N-ASF",
      "strongs": "G1546",
      "metadata": {},
      "gematria": {
        "standard": 185,
        "ordinal": 28,
        "reduced": 32
      }
    },
    {
      "position": 8,
      "text": "εποιουντο",
      "lemma": [
        "G4160"
      ],
      "morph": "robinson:V-IMI-3P",
      "strongs": "G4160",
      "metadata": {},
      "gematria": {
        "standard": 1055,
        "ordinal": 45,
        "reduced": 47
      }
    }
  ],
  "gematria": {
    "standard": 6220,
    "ordinal": 201,
    "reduced": 226
  }
}