{
  "text": "το μυστηριον το αποκεκρυμμενον απο των αιωνων και απο των γενεων νυνι δε εφανερωθη τοις αγιοις αυτου",
  "words": [
    {
      "position": 1,
      "text": "το",
      "lemma": [
        "G3588"
      ],
      "morph": "robinson:T-ASN",
      "strongs": "G3588",
      "metadata": {},
      "gematria": {
        "standard": 370,
        "ordinal": 3,
        "reduced": 10
      }
    },
    {
      "position": 2,
      "text": "μυστηριον",
      "lemma": [
        "G3466"
      ],
      "morph": "robinson:N-ASN",
      "strongs": "G3466",
      "metadata": {},
      "gematria": {
        "standard": 1178,
        "ordinal": 45,
        "reduced": 35
      }
    },
    {
      "position": 3,
      "text": "το",
      "lemma": [
        "G3588"
      ],
      "morph": "robinson:T-ASN",
      "strongs": "G3588",
      "metadata": {},
      "gematria": {
        "standard": 370,
        "ordinal": 3,
        "reduced": 10
      }
    },
    {
      "position": 4,
      "text": "αποκεκρυμμενον",
      "lemma": [
        "G613"
      ],
      "morph": "robinson:V-RPP-ASN",
      "strongs": "G613",
      "metadata": {},
      "gematria": {
        "standard": 951,
        "ordinal": 105,
        "reduced": 60
      }
    },
    {
      "position": 5,
      "text": "απο",
      "lemma": [
        "G575"
      ],
      "morph": "robinson:PREP",
      "strongs": "G575",
      "metadata": {},
      "gematria": {
        "standard": 151,
        "ordinal": 6,
        "reduced": 16
      }
    },
    {
      "position": 6,
      "text": "των",
      "lemma": [
        "G3588"
      ],
      "morph": "robinson:T-GPM",
      "strongs": "G3588",
      "metadata": {},
      "gematria": {
        "standard": 1150,
        "ordinal": 6,
        "reduced": 16
      }
    },
    {
      "position": 7,
      "text": "αιωνων",
      "lemma": [
        "G165"
      ],
      "morph": "robinson:N-GPM",
      "strongs": "G165",
      "metadata": {},
      "gematria": {
        "standard": 1711,
        "ordinal": 21,
        "reduced": 28
      }
    },
    {
      "position": 8,
      "text": "και",
      "lemma": [
        "G2532"
      ],
      "morph": "robinson:CONJ",
      "strongs": "G2532",
      "metadata": {},
      "gematria": {
        "standard": 31,
        "ordinal": 6,
        "reduced": 4
      }
    },
    {
      "position": 9,
      "text": "απο",
      "lemma": [
        "G575"
      ],
      "morph": "robinson:PREP",
      "strongs": "G575",
      "metadata": {},
      "gematria": {
        "standard": 151,
        "ordinal": 6,
        "reduced": 16
      }
    },
    {
      "position": 10,
      "text": "των",
      "lemma": [
        "G3588"
      ],
      "morph": "robinson:T-GPF",
      "strongs": "G3588",
      "metadata": {},
      "gematria": {
        "standard": 1150,
        "ordinal": 6,
        "reduced": 16
      }
    },
    {
      "position": 11,
      "text": "γενεων",
      "lemma": [
        "G1074"
      ],
      "morph": "robinson:N-GPF",
      "strongs": "G1074",
      "metadata": {},
      "gematria": {
        "standard": 913,
        "ordinal": 21,
        "reduced": 31
      }
    },
    {
      "position": 12,
      "text": "νυνι",
      "lemma": [
        "G3570"
      ],
      "morph": "robinson:ADV",
      "strongs": "G3570",
      "metadata": {},
      "gematria": {
        "standard": 510,
        "ordinal": 10,
        "reduced": 15
      }
    },
    {
      "position": 13,
      "text": "δε",
      "lemma": [
        "G1161"
      ],
      "morph": "robinson:CONJ",
      "strongs": "G1161",
      "metadata": {},
      "gematria": {
        "standard": 9,
        "ordinal": 3,
        "reduced": 9
      }
    },
    {
      "position": 14,
      "text": "εφανερωθη",
      "lemma": [
        "G5319"
      ],
      "morph": "robinson:V-API-3S",
      "strongs": "G5319",
      "metadata": {},
      "gematria": {
        "standard": 1478,
        "ordinal": 45,
        "reduced": 47
      }
    },
    {
      "position": 15,
      "text": "τοις",
      "lemma": [
        "G3588"
      ],
      "morph": "robinson:T-DPM",
      "strongs": "G3588",
      "metadata": {},
      "gematria": {
        "standard": 580,
        "ordinal": 10,
        "reduced": 13
      }
    },
    {
      "position": 16,
      "text": "αγιοις",
      "lemma": [
        "G40"
      ],
      "morph": "robinson:A-DPM",
      "strongs": "G40",
      "metadata": {},
      "gematria": {
        "standard": 294,
        "ordinal": 21,
        "reduced": 15
      }
    },
    {
      "position": 17,
      "text": "αυτου",
      "lemma": [
        "G846"
      ],
      "morph": "robinson:P-GSM",
      "strongs": "G846",
      "metadata": {},
      "gematria": {
        "standard": 1171,
        "ordinal": 15,
        "reduced": 19
      }
    }
  ],
  "gematria": {
    "standard": 12168,
    "ordinal": 332,
    "reduced": 360
  }
}