{
  "text": "αλλα και αι τριχες της κεφαλης υμων πασαι ηριθμηνται μη ουν φοβεισθε πολλων στρουθιων διαφερετε",
  "words": [
    {
      "position": 1,
      "text": "αλλα",
      "lemma": [
        "G235"
      ],
      "morph": "robinson:CONJ",
      "strongs": "G235",
      "metadata": {},
      "gematria": {
        "standard": 62,
        "ordinal": 24,
        "reduced": 8
      }
    },
    {
      "position": 2,
      "text": "και",
      "lemma": [
        "G2532"
      ],
      "morph": "robinson:CONJ",
      "strongs": "G2532",
      "metadata": {},
      "gematria": {
        "standard": 31,
        "ordinal": 20,
        "reduced": 4
      }
    },
    {
      "position": 3,
      "text": "αι",
      "lemma": [
        "G3588"
      ],
      "morph": "robinson:T-NPF",
      "strongs": "G3588",
      "metadata": {},
      "gematria": {
        "standard": 11,
        "ordinal": 10,
        "reduced": 2
      }
    },
    {
      "position": 4,
      "text": "τριχες",
      "lemma": [
        "G2359"
      ],
      "morph": "robinson:N-NPF",
      "strongs": "G2359",
      "metadata": {},
      "gematria": {
        "standard": 1215,
        "ordinal": 90,
        "reduced": 9
      }
    },
    {
      "position": 5,
      "text": "της",
      "lemma": [
        "G3588"
      ],
      "morph": "robinson:T-GSF",
      "strongs": "G3588",
      "metadata": {},
      "gematria": {
        "standard": 508,
        "ordinal": 44,
        "reduced": 4
      }
    },
    {
      "position": 6,
      "text": "κεφαλης",
      "lemma": [
        "G2776"
      ],
      "morph": "robinson:N-GSF",
      "strongs": "G2776",
      "metadata": {},
      "gematria": {
        "standard": 764,
        "ordinal": 73,
        "reduced": 8
      }
    },
    {
      "position": 7,
      "text": "υμων",
      "lemma": [
        "G4771"
      ],
      "morph": "robinson:P-2GP",
      "strongs": "G4771",
      "metadata": {},
      "gematria": {
        "standard": 1290,
        "ordinal": 69,
        "reduced": 3
      }
    },
    {
      "position": 8,
      "text": "πασαι",
      "lemma": [
        "G3956"
      ],
      "morph": "robinson:A-NPF",
      "strongs": "G3956",
      "metadata": {},
      "gematria": {
        "standard": 292,
        "ordinal": 45,
        "reduced": 4
      }
    },
    {
      "position": 9,
      "text": "ηριθμηνται",
      "lemma": [
        "G705"
      ],
      "morph": "robinson:V-RPI-3P",
      "strongs": "G705",
      "metadata": {},
      "gematria": {
        "standard": 536,
        "ordinal": 102,
        "reduced": 5
      }
    },
    {
      "position": 10,
      "text": "μη",
      "lemma": [
        "G3361"
      ],
      "morph": "robinson:PRT-N",
      "strongs": "G3361",
      "metadata": {},
      "gematria": {
        "standard": 48,
        "ordinal": 19,
        "reduced": 3
      }
    },
    {
      "position": 11,
      "text": "ουν",
      "lemma": [
        "G3767"
      ],
      "morph": "robinson:CONJ",
      "strongs": "G3767",
      "metadata": {},
      "gematria": {
        "standard": 520,
        "ordinal": 48,
        "reduced": 7
      }
    },
    {
      "position": 12,
      "text": "φοβεισθε",
      "lemma": [
        "G5399"
      ],
      "morph": "robinson:V-PNM-2P",
      "strongs": "G5399",
      "metadata": {},
      "gematria": {
        "standard": 801,
        "ordinal": 83,
        "reduced": 9
      }
    },
    {
      "position": 13,
      "text": "πολλων",
      "lemma": [
        "G4183"
      ],
      "morph": "robinson:A-GPN",
      "strongs": "G4183",
      "metadata": {},
      "gematria": {
        "standard": 1060,
        "ordinal": 90,
        "reduced": 7
      }
    },
    {
      "position": 14,
      "text": "στρουθιων",
      "lemma": [
        "G4765"
      ],
      "morph": "robinson:N-GPN",
      "strongs": "G4765",
      "metadata": {},
      "gematria": {
        "standard": 1939,
        "ordinal": 143,
        "reduced": 4
      }
    },
    {
      "position": 15,
      "text": "διαφερετε",
      "lemma": [
        "G1308"
      ],
      "morph": "robinson:V-PAI-2P",
      "strongs": "G1308",
      "metadata": {},
      "gematria": {
        "standard": 930,
        "ordinal": 86,
        "reduced": 3
      }
    }
  ],
  "gematria": {
    "standard": 10007,
    "ordinal": 946,
    "reduced": 80
  }
}