{
  "text": "και φωνησας φωνη μεγαλη ο ιησους ειπεν πατερ εις χειρας σου παραθησομαι το πνευμα μου και ταυτα ειπων εxεπνευσεν",
  "words": [
    {
      "position": 1,
      "text": "και",
      "lemma": [
        "G2532"
      ],
      "morph": "robinson:CONJ",
      "strongs": "G2532",
      "metadata": {},
      "gematria": {
        "standard": 31,
        "ordinal": 20,
        "reduced": 4
      }
    },
    {
      "position": 2,
      "text": "φωνησας",
      "lemma": [
        "G5455"
      ],
      "morph": "robinson:V-AAP-NSM",
      "strongs": "G5455",
      "metadata": {},
      "gematria": {
        "standard": 1759,
        "ordinal": 102,
        "reduced": 4
      }
    },
    {
      "position": 3,
      "text": "φωνη",
      "lemma": [
        "G5456"
      ],
      "morph": "robinson:N-DSF",
      "strongs": "G5456",
      "metadata": {},
      "gematria": {
        "standard": 1358,
        "ordinal": 65,
        "reduced": 8
      }
    },
    {
      "position": 4,
      "text": "μεγαλη",
      "lemma": [
        "G3173"
      ],
      "morph": "robinson:A-DSF",
      "strongs": "G3173",
      "metadata": {},
      "gematria": {
        "standard": 87,
        "ordinal": 39,
        "reduced": 6
      }
    },
    {
      "position": 5,
      "text": "ο",
      "lemma": [
        "G3588"
      ],
      "morph": "robinson:T-NSM",
      "strongs": "G3588",
      "metadata": {},
      "gematria": {
        "standard": 70,
        "ordinal": 15,
        "reduced": 7
      }
    },
    {
      "position": 6,
      "text": "ιησους",
      "lemma": [
        "G2424"
      ],
      "morph": "robinson:N-NSM",
      "strongs": "G2424",
      "metadata": {},
      "gematria": {
        "standard": 888,
        "ordinal": 87,
        "reduced": 6
      }
    },
    {
      "position": 7,
      "text": "ειπεν",
      "lemma": [
        "G3004"
      ],
      "morph": "robinson:V-2AAI-3S",
      "strongs": "G3004",
      "metadata": {},
      "gematria": {
        "standard": 150,
        "ordinal": 48,
        "reduced": 6
      }
    },
    {
      "position": 8,
      "text": "πατερ",
      "lemma": [
        "G3962"
      ],
      "morph": "robinson:N-VSM",
      "strongs": "G3962",
      "metadata": {},
      "gematria": {
        "standard": 486,
        "ordinal": 58,
        "reduced": 9
      }
    },
    {
      "position": 9,
      "text": "εις",
      "lemma": [
        "G1519"
      ],
      "morph": "robinson:PREP",
      "strongs": "G1519",
      "metadata": {},
      "gematria": {
        "standard": 215,
        "ordinal": 32,
        "reduced": 8
      }
    },
    {
      "position": 10,
      "text": "χειρας",
      "lemma": [
        "G5495"
      ],
      "morph": "robinson:N-APF",
      "strongs": "G5495",
      "metadata": {},
      "gematria": {
        "standard": 916,
        "ordinal": 72,
        "reduced": 7
      }
    },
    {
      "position": 11,
      "text": "σου",
      "lemma": [
        "G4771"
      ],
      "morph": "robinson:P-2GS",
      "strongs": "G4771",
      "metadata": {},
      "gematria": {
        "standard": 670,
        "ordinal": 53,
        "reduced": 4
      }
    },
    {
      "position": 12,
      "text": "παραθησομαι",
      "lemma": [
        "G3908"
      ],
      "morph": "robinson:V-FDI-1S",
      "strongs": "G3908",
      "metadata": {},
      "gematria": {
        "standard": 520,
        "ordinal": 105,
        "reduced": 7
      }
    },
    {
      "position": 13,
      "text": "το",
      "lemma": [
        "G3588"
      ],
      "morph": "robinson:T-ASN",
      "strongs": "G3588",
      "metadata": {},
      "gematria": {
        "standard": 370,
        "ordinal": 34,
        "reduced": 1
      }
    },
    {
      "position": 14,
      "text": "πνευμα",
      "lemma": [
        "G4151"
      ],
      "morph": "robinson:N-ASN",
      "strongs": "G4151",
      "metadata": {},
      "gematria": {
        "standard": 576,
        "ordinal": 67,
        "reduced": 9
      }
    },
    {
      "position": 15,
      "text": "μου",
      "lemma": [
        "G1473"
      ],
      "morph": "robinson:P-1GS",
      "strongs": "G1473",
      "metadata": {},
      "gematria": {
        "standard": 510,
        "ordinal": 47,
        "reduced": 6
      }
    },
    {
      "position": 16,
      "text": "και",
      "lemma": [
        "G2532"
      ],
      "morph": "robinson:CONJ",
      "strongs": "G2532",
      "metadata": {},
      "gematria": {
        "standard": 31,
        "ordinal": 20,
        "reduced": 4
      }
    },
    {
      "position": 17,
      "text": "ταυτα",
      "lemma": [
        "G3778"
      ],
      "morph": "robinson:D-APN",
      "strongs": "G3778",
      "metadata": {},
      "gematria": {
        "standard": 1002,
        "ordinal": 60,
        "reduced": 3
      }
    },
    {
      "position": 18,
      "text": "ειπων",
      "lemma": [
        "G3004"
      ],
      "morph": "robinson:V-2AAP-NSM",
      "strongs": "G3004",
      "metadata": {},
      "gematria": {
        "standard": 945,
        "ordinal": 67,
        "reduced": 9
      }
    },
    {
      "position": 19,
      "text": "εxεπνευσεν",
      "lemma": [
        "G1606"
      ],
      "morph": "robinson:V-AAI-3S",
      "strongs": "G1606",
      "metadata": {},
      "gematria": {
        "standard": 800,
        "ordinal": 100,
        "reduced": 8
      }
    }
  ],
  "gematria": {
    "standard": 11384,
    "ordinal": 1091,
    "reduced": 116
  }
}