{
  "text": "επειτα ωφθη ιακωβω ειτα τοις αποστολοις πασιν",
  "words": [
    {
      "position": 1,
      "text": "επειτα",
      "lemma": [
        "G1899"
      ],
      "morph": "robinson:ADV",
      "strongs": "G1899",
      "metadata": {},
      "gematria": {
        "standard": 401,
        "ordinal": 55,
        "reduced": 5
      }
    },
    {
      "position": 2,
      "text": "ωφθη",
      "lemma": [
        "G3708"
      ],
      "morph": "robinson:V-API-3S",
      "strongs": "G3708",
      "metadata": {},
      "gematria": {
        "standard": 1317,
        "ordinal": 60,
        "reduced": 3
      }
    },
    {
      "position": 3,
      "text": "ιακωβω",
      "lemma": [
        "G2385"
      ],
      "morph": "robinson:N-DSM",
      "strongs": "G2385",
      "metadata": {},
      "gematria": {
        "standard": 1633,
        "ordinal": 70,
        "reduced": 4
      }
    },
    {
      "position": 4,
      "text": "ειτα",
      "lemma": [
        "G1534"
      ],
      "morph": "robinson:ADV",
      "strongs": "G1534",
      "metadata": {},
      "gematria": {
        "standard": 316,
        "ordinal": 34,
        "reduced": 1
      }
    },
    {
      "position": 5,
      "text": "τοις",
      "lemma": [
        "G3588"
      ],
      "morph": "robinson:T-DPM",
      "strongs": "G3588",
      "metadata": {},
      "gematria": {
        "standard": 580,
        "ordinal": 61,
        "reduced": 4
      }
    },
    {
      "position": 6,
      "text": "αποστολοις",
      "lemma": [
        "G652"
      ],
      "morph": "robinson:N-DPM",
      "strongs": "G652",
      "metadata": {},
      "gematria": {
        "standard": 1031,
        "ordinal": 137,
        "reduced": 5
      }
    },
    {
      "position": 7,
      "text": "πασιν",
      "lemma": [
        "G3956"
      ],
      "morph": "robinson:A-DPM",
      "strongs": "G3956",
      "metadata": {},
      "gematria": {
        "standard": 341,
        "ordinal": 57,
        "reduced": 8
      }
    }
  ],
  "gematria": {
    "standard": 5619,
    "ordinal": 474,
    "reduced": 30
  }
}