{
  "text": "και τα αγενη του κοσμου και τα εxουθενημενα εxελεxατο ο θεος και τα μη οντα ινα τα οντα καταργηση",
  "words": [
    {
      "position": 1,
      "text": "και",
      "lemma": [
        "G2532"
      ],
      "morph": "robinson:CONJ",
      "strongs": "G2532",
      "metadata": {},
      "gematria": {
        "standard": 31,
        "ordinal": 6,
        "reduced": 4
      }
    },
    {
      "position": 2,
      "text": "τα",
      "lemma": [
        "G3588"
      ],
      "morph": "robinson:T-APN",
      "strongs": "G3588",
      "metadata": {},
      "gematria": {
        "standard": 301,
        "ordinal": 3,
        "reduced": 4
      }
    },
    {
      "position": 3,
      "text": "αγενη",
      "lemma": [
        "G36"
      ],
      "morph": "robinson:A-APN",
      "strongs": "G36",
      "metadata": {},
      "gematria": {
        "standard": 67,
        "ordinal": 15,
        "reduced": 22
      }
    },
    {
      "position": 4,
      "text": "του",
      "lemma": [
        "G3588"
      ],
      "morph": "robinson:T-GSM",
      "strongs": "G3588",
      "metadata": {},
      "gematria": {
        "standard": 770,
        "ordinal": 6,
        "reduced": 14
      }
    },
    {
      "position": 5,
      "text": "κοσμου",
      "lemma": [
        "G2889"
      ],
      "morph": "robinson:N-GSM",
      "strongs": "G2889",
      "metadata": {},
      "gematria": {
        "standard": 800,
        "ordinal": 21,
        "reduced": 26
      }
    },
    {
      "position": 6,
      "text": "και",
      "lemma": [
        "G2532"
      ],
      "morph": "robinson:CONJ",
      "strongs": "G2532",
      "metadata": {},
      "gematria": {
        "standard": 31,
        "ordinal": 6,
        "reduced": 4
      }
    },
    {
      "position": 7,
      "text": "τα",
      "lemma": [
        "G3588"
      ],
      "morph": "robinson:T-APN",
      "strongs": "G3588",
      "metadata": {},
      "gematria": {
        "standard": 301,
        "ordinal": 3,
        "reduced": 4
      }
    },
    {
      "position": 8,
      "text": "εxουθενημενα",
      "lemma": [
        "G1848"
      ],
      "morph": "robinson:V-RPP-APN",
      "strongs": "G1848",
      "metadata": {},
      "gematria": {
        "standard": 643,
        "ordinal": 66,
        "reduced": 58
      }
    },
    {
      "position": 9,
      "text": "εxελεxατο",
      "lemma": [
        "G1586"
      ],
      "morph": "robinson:V-AMI-3S",
      "strongs": "G1586",
      "metadata": {},
      "gematria": {
        "standard": 416,
        "ordinal": 28,
        "reduced": 29
      }
    },
    {
      "position": 10,
      "text": "ο",
      "lemma": [
        "G3588"
      ],
      "morph": "robinson:T-NSM",
      "strongs": "G3588",
      "metadata": {},
      "gematria": {
        "standard": 70,
        "ordinal": 1,
        "reduced": 7
      }
    },
    {
      "position": 11,
      "text": "θεος",
      "lemma": [
        "G2316"
      ],
      "morph": "robinson:N-NSM",
      "strongs": "G2316",
      "metadata": {},
      "gematria": {
        "standard": 284,
        "ordinal": 10,
        "reduced": 23
      }
    },
    {
      "position": 12,
      "text": "και",
      "lemma": [
        "G2532"
      ],
      "morph": "robinson:CONJ",
      "strongs": "G2532",
      "metadata": {},
      "gematria": {
        "standard": 31,
        "ordinal": 6,
        "reduced": 4
      }
    },
    {
      "position": 13,
      "text": "τα",
      "lemma": [
        "G3588"
      ],
      "morph": "robinson:T-APN",
      "strongs": "G3588",
      "metadata": {},
      "gematria": {
        "standard": 301,
        "ordinal": 3,
        "reduced": 4
      }
    },
    {
      "position": 14,
      "text": "μη",
      "lemma": [
        "G3361"
      ],
      "morph": "robinson:PRT-N",
      "strongs": "G3361",
      "metadata": {},
      "gematria": {
        "standard": 48,
        "ordinal": 3,
        "reduced": 12
      }
    },
    {
      "position": 15,
      "text": "οντα",
      "lemma": [
        "G1510"
      ],
      "morph": "robinson:V-PAP-APN",
      "strongs": "G1510",
      "metadata": {},
      "gematria": {
        "standard": 421,
        "ordinal": 10,
        "reduced": 16
      }
    },
    {
      "position": 16,
      "text": "ινα",
      "lemma": [
        "G2443"
      ],
      "morph": "robinson:CONJ",
      "strongs": "G2443",
      "metadata": {},
      "gematria": {
        "standard": 61,
        "ordinal": 6,
        "reduced": 7
      }
    },
    {
      "position": 17,
      "text": "τα",
      "lemma": [
        "G3588"
      ],
      "morph": "robinson:T-APN",
      "strongs": "G3588",
      "metadata": {},
      "gematria": {
        "standard": 301,
        "ordinal": 3,
        "reduced": 4
      }
    },
    {
      "position": 18,
      "text": "οντα",
      "lemma": [
        "G1510"
      ],
      "morph": "robinson:V-PAP-APN",
      "strongs": "G1510",
      "metadata": {},
      "gematria": {
        "standard": 421,
        "ordinal": 10,
        "reduced": 16
      }
    },
    {
      "position": 19,
      "text": "καταργηση",
      "lemma": [
        "G2673"
      ],
      "morph": "robinson:V-AAS-3S",
      "strongs": "G2673",
      "metadata": {},
      "gematria": {
        "standard": 641,
        "ordinal": 45,
        "reduced": 29
      }
    }
  ],
  "gematria": {
    "standard": 5939,
    "ordinal": 251,
    "reduced": 287
  }
}