{
  "text": "γενεσιων δε αγομενων του ηρωδου ωρχησατο η θυγατηρ της ηρωδιαδος εν τω μεσω και ηρεσεν τω ηρωδη",
  "words": [
    {
      "position": 1,
      "text": "γενεσιων",
      "lemma": [
        "G1077"
      ],
      "morph": "robinson:N-GPN",
      "strongs": "G1077",
      "metadata": {},
      "gematria": {
        "standard": 1123,
        "ordinal": 90,
        "reduced": 7
      }
    },
    {
      "position": 2,
      "text": "δε",
      "lemma": [
        "G1161"
      ],
      "morph": "robinson:CONJ",
      "strongs": "G1161",
      "metadata": {},
      "gematria": {
        "standard": 9,
        "ordinal": 9,
        "reduced": 9
      }
    },
    {
      "position": 3,
      "text": "αγομενων",
      "lemma": [
        "G71"
      ],
      "morph": "robinson:V-PPP-GPN",
      "strongs": "G71",
      "metadata": {},
      "gematria": {
        "standard": 1019,
        "ordinal": 86,
        "reduced": 2
      }
    },
    {
      "position": 4,
      "text": "του",
      "lemma": [
        "G3588"
      ],
      "morph": "robinson:T-GSM",
      "strongs": "G3588",
      "metadata": {},
      "gematria": {
        "standard": 770,
        "ordinal": 54,
        "reduced": 5
      }
    },
    {
      "position": 5,
      "text": "ηρωδου",
      "lemma": [
        "G2264"
      ],
      "morph": "robinson:N-GSM",
      "strongs": "G2264",
      "metadata": {},
      "gematria": {
        "standard": 1382,
        "ordinal": 87,
        "reduced": 5
      }
    },
    {
      "position": 6,
      "text": "ωρχησατο",
      "lemma": [
        "G3738"
      ],
      "morph": "robinson:V-ADI-3S",
      "strongs": "G3738",
      "metadata": {},
      "gematria": {
        "standard": 2079,
        "ordinal": 123,
        "reduced": 9
      }
    },
    {
      "position": 7,
      "text": "η",
      "lemma": [
        "G3588"
      ],
      "morph": "robinson:T-NSF",
      "strongs": "G3588",
      "metadata": {},
      "gematria": {
        "standard": 8,
        "ordinal": 7,
        "reduced": 8
      }
    },
    {
      "position": 8,
      "text": "θυγατηρ",
      "lemma": [
        "G2364"
      ],
      "morph": "robinson:N-NSF",
      "strongs": "G2364",
      "metadata": {},
      "gematria": {
        "standard": 821,
        "ordinal": 75,
        "reduced": 2
      }
    },
    {
      "position": 9,
      "text": "της",
      "lemma": [
        "G3588"
      ],
      "morph": "robinson:T-GSF",
      "strongs": "G3588",
      "metadata": {},
      "gematria": {
        "standard": 508,
        "ordinal": 44,
        "reduced": 4
      }
    },
    {
      "position": 10,
      "text": "ηρωδιαδος",
      "lemma": [
        "G2266"
      ],
      "morph": "robinson:N-GSF",
      "strongs": "G2266",
      "metadata": {},
      "gematria": {
        "standard": 1197,
        "ordinal": 99,
        "reduced": 9
      }
    },
    {
      "position": 11,
      "text": "εν",
      "lemma": [
        "G1722"
      ],
      "morph": "robinson:PREP",
      "strongs": "G1722",
      "metadata": {},
      "gematria": {
        "standard": 55,
        "ordinal": 18,
        "reduced": 1
      }
    },
    {
      "position": 12,
      "text": "τω",
      "lemma": [
        "G3588"
      ],
      "morph": "robinson:T-DSN",
      "strongs": "G3588",
      "metadata": {},
      "gematria": {
        "standard": 1100,
        "ordinal": 43,
        "reduced": 2
      }
    },
    {
      "position": 13,
      "text": "μεσω",
      "lemma": [
        "G3319"
      ],
      "morph": "robinson:A-DSN",
      "strongs": "G3319",
      "metadata": {},
      "gematria": {
        "standard": 1045,
        "ordinal": 59,
        "reduced": 1
      }
    },
    {
      "position": 14,
      "text": "και",
      "lemma": [
        "G2532"
      ],
      "morph": "robinson:CONJ",
      "strongs": "G2532",
      "metadata": {},
      "gematria": {
        "standard": 31,
        "ordinal": 20,
        "reduced": 4
      }
    },
    {
      "position": 15,
      "text": "ηρεσεν",
      "lemma": [
        "G700"
      ],
      "morph": "robinson:V-AAI-3S",
      "strongs": "G700",
      "metadata": {},
      "gematria": {
        "standard": 368,
        "ordinal": 65,
        "reduced": 8
      }
    },
    {
      "position": 16,
      "text": "τω",
      "lemma": [
        "G3588"
      ],
      "morph": "robinson:T-DSM",
      "strongs": "G3588",
      "metadata": {},
      "gematria": {
        "standard": 1100,
        "ordinal": 43,
        "reduced": 2
      }
    },
    {
      "position": 17,
      "text": "ηρωδη",
      "lemma": [
        "G2264"
      ],
      "morph": "robinson:N-DSM",
      "strongs": "G2264",
      "metadata": {},
      "gematria": {
        "standard": 920,
        "ordinal": 59,
        "reduced": 2
      }
    }
  ],
  "gematria": {
    "standard": 13535,
    "ordinal": 981,
    "reduced": 80
  }
}