{
  "text": "οι δε ανθρωποι εθαυμασαν λεγοντες ποταπος εστιν ουτος οτι και οι ανεμοι και η θαλασσα υπακουουσιν αυτω",
  "words": [
    {
      "position": 1,
      "text": "οι",
      "lemma": [
        "G3588"
      ],
      "morph": "robinson:T-NPM",
      "strongs": "G3588",
      "metadata": {},
      "gematria": {
        "standard": 80,
        "ordinal": 24,
        "reduced": 8
      }
    },
    {
      "position": 2,
      "text": "δε",
      "lemma": [
        "G1161"
      ],
      "morph": "robinson:CONJ",
      "strongs": "G1161",
      "metadata": {},
      "gematria": {
        "standard": 9,
        "ordinal": 9,
        "reduced": 9
      }
    },
    {
      "position": 3,
      "text": "ανθρωποι",
      "lemma": [
        "G444"
      ],
      "morph": "robinson:N-NPM",
      "strongs": "G444",
      "metadata": {},
      "gematria": {
        "standard": 1120,
        "ordinal": 103,
        "reduced": 4
      }
    },
    {
      "position": 4,
      "text": "εθαυμασαν",
      "lemma": [
        "G2296"
      ],
      "morph": "robinson:V-AAI-3P",
      "strongs": "G2296",
      "metadata": {},
      "gematria": {
        "standard": 707,
        "ordinal": 79,
        "reduced": 5
      }
    },
    {
      "position": 5,
      "text": "λεγοντες",
      "lemma": [
        "G3004"
      ],
      "morph": "robinson:V-PAP-NPM",
      "strongs": "G3004",
      "metadata": {},
      "gematria": {
        "standard": 663,
        "ordinal": 89,
        "reduced": 6
      }
    },
    {
      "position": 6,
      "text": "ποταπος",
      "lemma": [
        "G4217"
      ],
      "morph": "robinson:A-NSM",
      "strongs": "G4217",
      "metadata": {},
      "gematria": {
        "standard": 801,
        "ordinal": 100,
        "reduced": 9
      }
    },
    {
      "position": 7,
      "text": "εστιν",
      "lemma": [
        "G1510"
      ],
      "morph": "robinson:V-PAI-3S",
      "strongs": "G1510",
      "metadata": {},
      "gematria": {
        "standard": 565,
        "ordinal": 64,
        "reduced": 7
      }
    },
    {
      "position": 8,
      "text": "ουτος",
      "lemma": [
        "G3778"
      ],
      "morph": "robinson:D-NSM",
      "strongs": "G3778",
      "metadata": {},
      "gematria": {
        "standard": 1040,
        "ordinal": 87,
        "reduced": 5
      }
    },
    {
      "position": 9,
      "text": "οτι",
      "lemma": [
        "G3754"
      ],
      "morph": "robinson:CONJ",
      "strongs": "G3754",
      "metadata": {},
      "gematria": {
        "standard": 380,
        "ordinal": 43,
        "reduced": 2
      }
    },
    {
      "position": 10,
      "text": "και",
      "lemma": [
        "G2532"
      ],
      "morph": "robinson:CONJ",
      "strongs": "G2532",
      "metadata": {},
      "gematria": {
        "standard": 31,
        "ordinal": 20,
        "reduced": 4
      }
    },
    {
      "position": 11,
      "text": "οι",
      "lemma": [
        "G3588"
      ],
      "morph": "robinson:T-NPM",
      "strongs": "G3588",
      "metadata": {},
      "gematria": {
        "standard": 80,
        "ordinal": 24,
        "reduced": 8
      }
    },
    {
      "position": 12,
      "text": "ανεμοι",
      "lemma": [
        "G417"
      ],
      "morph": "robinson:N-NPM",
      "strongs": "G417",
      "metadata": {},
      "gematria": {
        "standard": 176,
        "ordinal": 55,
        "reduced": 5
      }
    },
    {
      "position": 13,
      "text": "και",
      "lemma": [
        "G2532"
      ],
      "morph": "robinson:CONJ",
      "strongs": "G2532",
      "metadata": {},
      "gematria": {
        "standard": 31,
        "ordinal": 20,
        "reduced": 4
      }
    },
    {
      "position": 14,
      "text": "η",
      "lemma": [
        "G3588"
      ],
      "morph": "robinson:T-NSF",
      "strongs": "G3588",
      "metadata": {},
      "gematria": {
        "standard": 8,
        "ordinal": 7,
        "reduced": 8
      }
    },
    {
      "position": 15,
      "text": "θαλασσα",
      "lemma": [
        "G2281"
      ],
      "morph": "robinson:N-NSF",
      "strongs": "G2281",
      "metadata": {},
      "gematria": {
        "standard": 442,
        "ordinal": 58,
        "reduced": 1
      }
    },
    {
      "position": 16,
      "text": "υπακουουσιν",
      "lemma": [
        "G5219"
      ],
      "morph": "robinson:V-PAI-3P",
      "strongs": "G5219",
      "metadata": {},
      "gematria": {
        "standard": 1701,
        "ordinal": 157,
        "reduced": 9
      }
    },
    {
      "position": 17,
      "text": "αυτω",
      "lemma": [
        "G846"
      ],
      "morph": "robinson:P-DSM",
      "strongs": "G846",
      "metadata": {},
      "gematria": {
        "standard": 1501,
        "ordinal": 64,
        "reduced": 7
      }
    }
  ],
  "gematria": {
    "standard": 9335,
    "ordinal": 1003,
    "reduced": 101
  }
}