{
  "text": "ως δε συνεβαλεν ημιν εις την ασσον αναλαβοντες αυτον ηλθομεν εις μιτυληνην",
  "words": [
    {
      "position": 1,
      "text": "ως",
      "lemma": [
        "G5613"
      ],
      "morph": "robinson:ADV",
      "strongs": "G5613",
      "metadata": {},
      "gematria": {
        "standard": 1000,
        "ordinal": 3,
        "reduced": 10
      }
    },
    {
      "position": 2,
      "text": "δε",
      "lemma": [
        "G1161"
      ],
      "morph": "robinson:CONJ",
      "strongs": "G1161",
      "metadata": {},
      "gematria": {
        "standard": 9,
        "ordinal": 3,
        "reduced": 9
      }
    },
    {
      "position": 3,
      "text": "συνεβαλεν",
      "lemma": [
        "G4820"
      ],
      "morph": "robinson:V-2AAI-3S",
      "strongs": "G4820",
      "metadata": {},
      "gematria": {
        "standard": 743,
        "ordinal": 45,
        "reduced": 32
      }
    },
    {
      "position": 4,
      "text": "ημιν",
      "lemma": [
        "G1473"
      ],
      "morph": "robinson:P-1DP",
      "strongs": "G1473",
      "metadata": {},
      "gematria": {
        "standard": 108,
        "ordinal": 10,
        "reduced": 18
      }
    },
    {
      "position": 5,
      "text": "εις",
      "lemma": [
        "G1519"
      ],
      "morph": "robinson:PREP",
      "strongs": "G1519",
      "metadata": {},
      "gematria": {
        "standard": 215,
        "ordinal": 6,
        "reduced": 8
      }
    },
    {
      "position": 6,
      "text": "την",
      "lemma": [
        "G3588"
      ],
      "morph": "robinson:T-ASF",
      "strongs": "G3588",
      "metadata": {},
      "gematria": {
        "standard": 358,
        "ordinal": 6,
        "reduced": 16
      }
    },
    {
      "position": 7,
      "text": "ασσον",
      "lemma": [
        "G789"
      ],
      "morph": "robinson:N-ASF",
      "strongs": "G789",
      "metadata": {},
      "gematria": {
        "standard": 521,
        "ordinal": 15,
        "reduced": 17
      }
    },
    {
      "position": 8,
      "text": "αναλαβοντες",
      "lemma": [
        "G353"
      ],
      "morph": "robinson:V-2AAP-NPM",
      "strongs": "G353",
      "metadata": {},
      "gematria": {
        "standard": 710,
        "ordinal": 66,
        "reduced": 35
      }
    },
    {
      "position": 9,
      "text": "αυτον",
      "lemma": [
        "G846"
      ],
      "morph": "robinson:P-ASM",
      "strongs": "G846",
      "metadata": {},
      "gematria": {
        "standard": 821,
        "ordinal": 15,
        "reduced": 20
      }
    },
    {
      "position": 10,
      "text": "ηλθομεν",
      "lemma": [
        "G2064"
      ],
      "morph": "robinson:V-2AAI-1P",
      "strongs": "G2064",
      "metadata": {},
      "gematria": {
        "standard": 212,
        "ordinal": 28,
        "reduced": 41
      }
    },
    {
      "position": 11,
      "text": "εις",
      "lemma": [
        "G1519"
      ],
      "morph": "robinson:PREP",
      "strongs": "G1519",
      "metadata": {},
      "gematria": {
        "standard": 215,
        "ordinal": 6,
        "reduced": 8
      }
    },
    {
      "position": 12,
      "text": "μιτυληνην",
      "lemma": [
        "G3412"
      ],
      "morph": "robinson:N-ASF",
      "strongs": "G3412",
      "metadata": {},
      "gematria": {
        "standard": 896,
        "ordinal": 45,
        "reduced": 41
      }
    }
  ],
  "gematria": {
    "standard": 5808,
    "ordinal": 248,
    "reduced": 255
  }
}