{
  "text": "και συναγονται οι αποστολοι προς τον ιησουν και απηγγειλαν αυτω παντα και οσα εποιησαν και οσα εδιδαxαν",
  "words": [
    {
      "position": 1,
      "text": "και",
      "lemma": [
        "G2532"
      ],
      "morph": "robinson:CONJ",
      "strongs": "G2532",
      "metadata": {},
      "gematria": {
        "standard": 31,
        "ordinal": 6,
        "reduced": 4
      }
    },
    {
      "position": 2,
      "text": "συναγονται",
      "lemma": [
        "G4863"
      ],
      "morph": "robinson:V-PPI-3P",
      "strongs": "G4863",
      "metadata": {},
      "gematria": {
        "standard": 1085,
        "ordinal": 55,
        "reduced": 32
      }
    },
    {
      "position": 3,
      "text": "οι",
      "lemma": [
        "G3588"
      ],
      "morph": "robinson:T-NPM",
      "strongs": "G3588",
      "metadata": {},
      "gematria": {
        "standard": 80,
        "ordinal": 3,
        "reduced": 8
      }
    },
    {
      "position": 4,
      "text": "αποστολοι",
      "lemma": [
        "G652"
      ],
      "morph": "robinson:N-NPM",
      "strongs": "G652",
      "metadata": {},
      "gematria": {
        "standard": 831,
        "ordinal": 45,
        "reduced": 39
      }
    },
    {
      "position": 5,
      "text": "προς",
      "lemma": [
        "G4314"
      ],
      "morph": "robinson:PREP",
      "strongs": "G4314",
      "metadata": {},
      "gematria": {
        "standard": 450,
        "ordinal": 10,
        "reduced": 18
      }
    },
    {
      "position": 6,
      "text": "τον",
      "lemma": [
        "G3588"
      ],
      "morph": "robinson:T-ASM",
      "strongs": "G3588",
      "metadata": {},
      "gematria": {
        "standard": 420,
        "ordinal": 6,
        "reduced": 15
      }
    },
    {
      "position": 7,
      "text": "ιησουν",
      "lemma": [
        "G2424"
      ],
      "morph": "robinson:N-ASM",
      "strongs": "G2424",
      "metadata": {},
      "gematria": {
        "standard": 738,
        "ordinal": 21,
        "reduced": 27
      }
    },
    {
      "position": 8,
      "text": "και",
      "lemma": [
        "G2532"
      ],
      "morph": "robinson:CONJ",
      "strongs": "G2532",
      "metadata": {},
      "gematria": {
        "standard": 31,
        "ordinal": 6,
        "reduced": 4
      }
    },
    {
      "position": 9,
      "text": "απηγγειλαν",
      "lemma": [
        "G518"
      ],
      "morph": "robinson:V-AAI-3P",
      "strongs": "G518",
      "metadata": {},
      "gematria": {
        "standard": 191,
        "ordinal": 55,
        "reduced": 38
      }
    },
    {
      "position": 10,
      "text": "αυτω",
      "lemma": [
        "G846"
      ],
      "morph": "robinson:P-DSM",
      "strongs": "G846",
      "metadata": {},
      "gematria": {
        "standard": 1501,
        "ordinal": 10,
        "reduced": 16
      }
    },
    {
      "position": 11,
      "text": "παντα",
      "lemma": [
        "G3956"
      ],
      "morph": "robinson:A-APN",
      "strongs": "G3956",
      "metadata": {},
      "gematria": {
        "standard": 432,
        "ordinal": 15,
        "reduced": 18
      }
    },
    {
      "position": 12,
      "text": "και",
      "lemma": [
        "G2532"
      ],
      "morph": "robinson:CONJ",
      "strongs": "G2532",
      "metadata": {},
      "gematria": {
        "standard": 31,
        "ordinal": 6,
        "reduced": 4
      }
    },
    {
      "position": 13,
      "text": "οσα",
      "lemma": [
        "G3745"
      ],
      "morph": "robinson:K-APN",
      "strongs": "G3745",
      "metadata": {},
      "gematria": {
        "standard": 271,
        "ordinal": 6,
        "reduced": 10
      }
    },
    {
      "position": 14,
      "text": "εποιησαν",
      "lemma": [
        "G4160"
      ],
      "morph": "robinson:V-AAI-3P",
      "strongs": "G4160",
      "metadata": {},
      "gematria": {
        "standard": 424,
        "ordinal": 36,
        "reduced": 37
      }
    },
    {
      "position": 15,
      "text": "και",
      "lemma": [
        "G2532"
      ],
      "morph": "robinson:CONJ",
      "strongs": "G2532",
      "metadata": {},
      "gematria": {
        "standard": 31,
        "ordinal": 6,
        "reduced": 4
      }
    },
    {
      "position": 16,
      "text": "οσα",
      "lemma": [
        "G3745"
      ],
      "morph": "robinson:K-APN",
      "strongs": "G3745",
      "metadata": {},
      "gematria": {
        "standard": 271,
        "ordinal": 6,
        "reduced": 10
      }
    },
    {
      "position": 17,
      "text": "εδιδαxαν",
      "lemma": [
        "G1321"
      ],
      "morph": "robinson:V-AAI-3P",
      "strongs": "G1321",
      "metadata": {},
      "gematria": {
        "standard": 75,
        "ordinal": 28,
        "reduced": 21
      }
    }
  ],
  "gematria": {
    "standard": 6893,
    "ordinal": 320,
    "reduced": 305
  }
}