{
  "text": "ανθρωπος δε τις ην πλουσιος και ενεδιδυσκετο πορφυραν και βυσσον ευφραινομενος καθ ημεραν λαμπρως",
  "words": [
    {
      "position": 1,
      "text": "ανθρωπος",
      "lemma": [
        "G444"
      ],
      "morph": "robinson:N-NSM",
      "strongs": "G444",
      "metadata": {},
      "gematria": {
        "standard": 1310,
        "ordinal": 36,
        "reduced": 41
      }
    },
    {
      "position": 2,
      "text": "δε",
      "lemma": [
        "G1161"
      ],
      "morph": "robinson:CONJ",
      "strongs": "G1161",
      "metadata": {},
      "gematria": {
        "standard": 9,
        "ordinal": 3,
        "reduced": 9
      }
    },
    {
      "position": 3,
      "text": "τις",
      "lemma": [
        "G5100"
      ],
      "morph": "robinson:X-NSM",
      "strongs": "G5100",
      "metadata": {},
      "gematria": {
        "standard": 510,
        "ordinal": 6,
        "reduced": 6
      }
    },
    {
      "position": 4,
      "text": "ην",
      "lemma": [
        "G1510"
      ],
      "morph": "robinson:V-IAI-3S",
      "strongs": "G1510",
      "metadata": {},
      "gematria": {
        "standard": 58,
        "ordinal": 3,
        "reduced": 13
      }
    },
    {
      "position": 5,
      "text": "πλουσιος",
      "lemma": [
        "G4145"
      ],
      "morph": "robinson:A-NSM",
      "strongs": "G4145",
      "metadata": {},
      "gematria": {
        "standard": 1060,
        "ordinal": 36,
        "reduced": 34
      }
    },
    {
      "position": 6,
      "text": "και",
      "lemma": [
        "G2532"
      ],
      "morph": "robinson:CONJ",
      "strongs": "G2532",
      "metadata": {},
      "gematria": {
        "standard": 31,
        "ordinal": 6,
        "reduced": 4
      }
    },
    {
      "position": 7,
      "text": "ενεδιδυσκετο",
      "lemma": [
        "G1737"
      ],
      "morph": "robinson:V-IMI-3S",
      "strongs": "G1737",
      "metadata": {},
      "gematria": {
        "standard": 1073,
        "ordinal": 78,
        "reduced": 47
      }
    },
    {
      "position": 8,
      "text": "πορφυραν",
      "lemma": [
        "G4209"
      ],
      "morph": "robinson:N-ASF",
      "strongs": "G4209",
      "metadata": {},
      "gematria": {
        "standard": 1301,
        "ordinal": 36,
        "reduced": 32
      }
    },
    {
      "position": 9,
      "text": "και",
      "lemma": [
        "G2532"
      ],
      "morph": "robinson:CONJ",
      "strongs": "G2532",
      "metadata": {},
      "gematria": {
        "standard": 31,
        "ordinal": 6,
        "reduced": 4
      }
    },
    {
      "position": 10,
      "text": "βυσσον",
      "lemma": [
        "G1040"
      ],
      "morph": "robinson:N-ASF",
      "strongs": "G1040",
      "metadata": {},
      "gematria": {
        "standard": 922,
        "ordinal": 21,
        "reduced": 22
      }
    },
    {
      "position": 11,
      "text": "ευφραινομενος",
      "lemma": [
        "G2165"
      ],
      "morph": "robinson:V-PPP-NSM",
      "strongs": "G2165",
      "metadata": {},
      "gematria": {
        "standard": 1501,
        "ordinal": 91,
        "reduced": 52
      }
    },
    {
      "position": 12,
      "text": "καθ",
      "lemma": [
        "G2596"
      ],
      "morph": "robinson:PREP",
      "strongs": "G2596",
      "metadata": {},
      "gematria": {
        "standard": 30,
        "ordinal": 6,
        "reduced": 12
      }
    },
    {
      "position": 13,
      "text": "ημεραν",
      "lemma": [
        "G2250"
      ],
      "morph": "robinson:N-ASF",
      "strongs": "G2250",
      "metadata": {},
      "gematria": {
        "standard": 204,
        "ordinal": 21,
        "reduced": 24
      }
    },
    {
      "position": 14,
      "text": "λαμπρως",
      "lemma": [
        "G2988"
      ],
      "morph": "robinson:ADV",
      "strongs": "G2988",
      "metadata": {},
      "gematria": {
        "standard": 1251,
        "ordinal": 28,
        "reduced": 27
      }
    }
  ],
  "gematria": {
    "standard": 9291,
    "ordinal": 377,
    "reduced": 327
  }
}